greenscreen/__init__.py
greenscreen-0.0.1.dist-info/METADATA
greenscreen-0.0.1.dist-info/WHEEL
greenscreen-0.0.1.dist-info/top_level.txt
greenscreen-0.0.1.dist-info/RECORD
